kdap/__init__.py
kdap/analysis.py
kdap/author_contrib.py
kdap/wikiStats.py
kdap/converter/__init__.py
kdap/converter/qaConverter.py
kdap/converter/wikiConverter.py
kdap/converter/wiki_clean.py
kdap/wiki_graph/__init__.py
kdap/wiki_graph/graph_creater.py
kdap/wikiextract/__init__.py
kdap/wikiextract/knolml_wikiextractor.py
kdap/wikiextract/sampleExtractdb.py
kdap/wikiextract/wikiExtract.py
tests/__init__.py
tests/test_analysis.py
tests/test_wikiExtract.py
kdap-0.1.29.dist-info/METADATA
kdap-0.1.29.dist-info/WHEEL
kdap-0.1.29.dist-info/top_level.txt
kdap-0.1.29.dist-info/RECORD
