Metadata-Version: 2.1
Name: kdap
Version: 0.1.29
Summary: KDAP is a package to analyze knowledge data
Home-page: https://kdap.github.io/
Author: Amit Arjun Verma
Author-email: mt4descentis@gmail.com
License: UNKNOWN
Platform: UNKNOWN
Classifier: Programming Language :: Python :: 3
Classifier: License :: OSI Approved :: BSD License
Classifier: Operating System :: OS Independent
Requires-Python: >=3.6
Requires-Dist: requests (==2.21.0)
Requires-Dist: internetarchive (==1.8.5)
Requires-Dist: numpy
Requires-Dist: wikipedia
Requires-Dist: pycountry
Requires-Dist: psutil (>=5.6.6)
Requires-Dist: mwparserfromhell (==0.5.4)
Requires-Dist: nltk (==3.4.5)
Requires-Dist: xmltodict
Requires-Dist: matplotlib
Requires-Dist: prettytable
Requires-Dist: bx-python
Requires-Dist: pyunpack
Requires-Dist: mwviews
Requires-Dist: patool
